infomaxy/__init__.py
infomaxy/config.py
infomaxy/version.py
infomaxy/api/__init__.py
infomaxy/api/imd.py
infomaxy/api/imutil.py
infomaxy-1.0.0.dist-info/LICENSE
infomaxy-1.0.0.dist-info/METADATA
infomaxy-1.0.0.dist-info/WHEEL
infomaxy-1.0.0.dist-info/top_level.txt
infomaxy-1.0.0.dist-info/RECORD
