Metadata-Version: 2.1
Name: infomaxy
Version: 1.0.0
Summary: Infomax Python API
Home-page: https://github.com/dimussong/infomaxy
Author: dimussong
Author-email: dimussong@gmail.com
License: UNKNOWN
Project-URL: Bug Tracker, https://github.com/dimussong/infomaxy/issues
Platform: UNKNOWN
Classifier: Programming Language :: Python :: 3
Classifier: License :: OSI Approved :: MIT License
Classifier: Operating System :: OS Independent
Requires-Python: >=3.6
License-File: LICENSE
